matrix_viewer/__init__.py
matrix_viewer/_custom_notebook.py
matrix_viewer/_manager.py
matrix_viewer/_tab.py
matrix_viewer/_tab_numpy.py
matrix_viewer/_tab_struct.py
matrix_viewer/_tab_table.py
matrix_viewer/_tab_text.py
matrix_viewer/_utils.py
matrix_viewer/_window.py
matrix_viewer-0.2.1.dist-info/LICENSE
matrix_viewer-0.2.1.dist-info/METADATA
matrix_viewer-0.2.1.dist-info/WHEEL
matrix_viewer-0.2.1.dist-info/entry_points.txt
matrix_viewer-0.2.1.dist-info/top_level.txt
matrix_viewer-0.2.1.dist-info/RECORD
