Metadata-Version: 2.2
Name: matrix_viewer
Version: 0.2.1
Summary: A tabular viewer for numpy arrays, python structs and more similar to the MATLAB data viewer
Home-page: https://github.com/msrst/matrix_viewer
Author: Matthias Rosenthal
License: MIT license
Keywords: matrix_viewer
Classifier: Development Status :: 2 - Pre-Alpha
Classifier: Intended Audience :: Developers
Classifier: License :: OSI Approved :: MIT License
Classifier: Natural Language :: English
Classifier: Programming Language :: Python :: 3
Classifier: Programming Language :: Python :: 3.6
Classifier: Programming Language :: Python :: 3.7
Classifier: Programming Language :: Python :: 3.8
Requires-Python: >=3.6
License-File: LICENSE
Requires-Dist: numpy>=1.0
Dynamic: author
Dynamic: classifier
Dynamic: description
Dynamic: home-page
Dynamic: keywords
Dynamic: license
Dynamic: requires-dist
Dynamic: requires-python
Dynamic: summary
